README.md
setup.py
ezspot/__init__.py
ezspot/__main__.py
ezspot/config.py
ezspot/config_loader.py
ezspot/ezspot.py
ezspot/request.py
ezspot/test.py
ezspot/version.py
ezspot/workload.py
ezspot.egg-info/PKG-INFO
ezspot.egg-info/SOURCES.txt
ezspot.egg-info/dependency_links.txt
ezspot.egg-info/entry_points.txt
ezspot.egg-info/requires.txt
ezspot.egg-info/top_level.txt
ezspot/libs/__init__.py
ezspot/libs/ami.py
ezspot/libs/availability_zone.py
ezspot/libs/aws_client.py
ezspot/libs/aws_lambda.py
ezspot/libs/cloudwatch_event.py
ezspot/libs/elastic_ip.py
ezspot/libs/iam_role.py
ezspot/libs/instance.py
ezspot/libs/logger.py
ezspot/libs/network_interface.py
ezspot/libs/price.py
ezspot/libs/resources.py
ezspot/libs/spot_fleet.py
ezspot/libs/spot_instance.py
ezspot/libs/subnet.py
ezspot/libs/vpc.py