Metadata-Version: 1.0
Name: ezspot
Version: 0.0.6
Summary: EZSpot - the spot management tool help you to use AWS EC2 spot instance easily. 
Home-page: https://github.com/finishy1995/ezspot
Author: David Wang 王元恺
Author-email: finishy@qq.com
License: MIT
Keywords: cli
Platform: UNKNOWN
